partial_sh/.DS_Store
partial_sh/__init__.py
partial_sh/api/__init__.py
partial_sh/api/auth.py
partial_sh/api/main.py
partial_sh/api/root.py
partial_sh/api/settings.py
partial_sh/api/shapers.py
partial_sh/api/state.py
partial_sh/auth_config.py
partial_sh/chains.py
partial_sh/cli.py
partial_sh/cloud_service.py
partial_sh/commands/__init__.py
partial_sh/commands/auth.py
partial_sh/commands/config.py
partial_sh/commands/demo.py
partial_sh/commands/examples.py
partial_sh/commands/functions.py
partial_sh/commands/login.py
partial_sh/commands/main.py
partial_sh/commands/push.py
partial_sh/commands/runs.py
partial_sh/commands/server.py
partial_sh/commands/setup.py
partial_sh/commands/shapers.py
partial_sh/commands/show.py
partial_sh/commands/utils.py
partial_sh/commands/ws.py
partial_sh/config.py
partial_sh/docker_sandbox.py
partial_sh/extract_imports.py
partial_sh/functions.py
partial_sh/input.py
partial_sh/instruction.py
partial_sh/json_schema.py
partial_sh/llm.py
partial_sh/local_execution.py
partial_sh/loggers.py
partial_sh/process.py
partial_sh/run.py
partial_sh/runner.py
partial_sh/runs.py
partial_sh/sandbox.py
partial_sh/sandboxes/Dockerfile.sandbox.python
partial_sh/shaper.py
partial_sh/store.py
partial_sh/tqdm_exp.py
partial_sh-0.7.2.dist-info/METADATA
partial_sh-0.7.2.dist-info/WHEEL
partial_sh-0.7.2.dist-info/entry_points.txt
partial_sh-0.7.2.dist-info/RECORD
