Metadata-Version: 2.1
Name: partial-sh
Version: 0.7.2
Summary: Manipulate JSON with your words
License: Apache-2.0
Author: Yanael Barbier
Author-email: st3w4r@gmail.com
Requires-Python: >=3.11,<4.0
Classifier: License :: OSI Approved :: Apache Software License
Classifier: Programming Language :: Python :: 3
Classifier: Programming Language :: Python :: 3.11
Classifier: Programming Language :: Python :: 3.12
Requires-Dist: docker (>=7.0.0,<8.0.0)
Requires-Dist: e2b (==0.17.1)
Requires-Dist: e2b-code-interpreter (>=0.0.10,<0.0.11)
Requires-Dist: fastapi (>=0.110.0,<0.111.0)
Requires-Dist: genson (>=1.2.2,<2.0.0)
Requires-Dist: jsonschema (>=4.21.1,<5.0.0)
Requires-Dist: langchain (==0.1.0)
Requires-Dist: langchain-community (>=0.0.11,<0.0.12)
Requires-Dist: langchain-openai (>=0.0.2,<0.0.3)
Requires-Dist: openai (==1.7.1)
Requires-Dist: pydantic-settings (>=2.2.1,<3.0.0)
Requires-Dist: pyjwt (>=2.8.0,<3.0.0)
Requires-Dist: rich (>=13.7.0,<14.0.0)
Requires-Dist: tabulate (>=0.9.0,<0.10.0)
Requires-Dist: tqdm (>=4.66.2,<5.0.0)
Requires-Dist: typer (==0.9.0)
Requires-Dist: uvicorn[standard] (>=0.27.1,<0.28.0)
